{
  "ep_length_mean": {
    "steps": [
      1
    ],
    "timestamps": [
      "2024-12-13T06:18:53.544585"
    ],
    "values": [
      1.0
    ]
  },
  "epsilon": {
    "steps": [
      1
    ],
    "timestamps": [
      "2024-12-13T06:18:53.544593"
    ],
    "values": [
      1.0
    ]
  },
  "return_mean": {
    "steps": [
      1
    ],
    "timestamps": [
      "2024-12-13T06:18:53.544516"
    ],
    "values": [
      0.0
    ]
  },
  "return_std": {
    "steps": [
      1
    ],
    "timestamps": [
      "2024-12-13T06:18:53.544573"
    ],
    "values": [
      0.0
    ]
  },
  "test_ep_length_mean": {
    "steps": [
      1
    ],
    "timestamps": [
      "2024-12-13T06:19:05.198527"
    ],
    "values": [
      1.0
    ]
  },
  "test_return_mean": {
    "steps": [
      1
    ],
    "timestamps": [
      "2024-12-13T06:19:05.198460"
    ],
    "values": [
      -0.01199999988079071
    ]
  },
  "test_return_std": {
    "steps": [
      1
    ],
    "timestamps": [
      "2024-12-13T06:19:05.198514"
    ],
    "values": [
      0.10027960898916172
    ]
  }
}